{"student_id":10024,"chats":{"before":[{"type":"chat","text":{"cn":"我预计会出远门一段时间","jp":"先生,そろそろ着きそう"},"sender":"student"},{"type":"chat","text":{"cn":"和大家也已经打过招呼了","jp":"もう出てきても大丈夫"},"sender":"student"},{"type":"chat","text":{"cn":"想着也和老师说一声比较好","jp":"出てきても大丈夫……？"},"sender":"teacher"},{"type":"chat","text":{"cn":"……出远门？","jp":"んと……"},"sender":"student"},{"type":"chat","text":{"cn":"没关系,不是什么大事","jp":"とにかく,出てきたらわかるから"},"sender":"student"},{"type":"chat","text":{"cn":"那么,再见了。老师","jp":"待ってるね"},"sender":"student"}],"after":[{"type":"chat","text":{"cn":"老师","jp":"そういえば"},"sender":"student"},{"type":"chat","text":{"cn":"刚好在休息,所以就试着联系了","jp":"今回,キヴォトス縦断ができたから"},"sender":"student"},{"type":"chat","text":{"cn":"难道说,已经骑了相当远了吗……？","jp":"次はキヴォトス横断をしてみようかなって"},"sender":"student"},{"type":"chat","text":{"cn":"嗯？","jp":"これも本当の横断じゃなくて,大体そんな感じってだけなんだけど"},"sender":"student"},{"type":"chat","text":{"cn":"没有,我还在刚刚和老师在一起的地方附近","jp":"先生さえよかったら,一緒に走ったり……"},"sender":"student"},{"type":"chat","text":{"cn":"正好是等红灯的空闲时间,所以就和老师联系了","jp":"実際の参加は,ちょっと……応援してるね"},"sender":"teacher"},{"type":"chat","text":{"cn":"……诶？","jp":"うーん……"},"sender":"student"},{"type":"chat","text":{"cn":"难道说所谓的停下来,不是这个时候吗？","jp":"そっか,残念"},"sender":"student"},{"type":"chat","text":{"cn":"抱歉,是我弄错了","jp":"じゃあ……これからも,サポーターとして"},"sender":"student"},{"type":"chat","text":{"cn":"那,嗯……等我下车休息的时候,再和老师联系吧","jp":"よろしくね,先生"},"sender":"student"}]}}